LICENSE
MANIFEST.in
README.rst
pyproject.toml
requirements.txt
setup.cfg
setup.py
pylibpcap/__init__.py
pylibpcap/__main__.py
pylibpcap/base.c
pylibpcap/cli.py
pylibpcap/exception.py
pylibpcap/open.py
pylibpcap/parse.py
pylibpcap/pcap.py
pylibpcap/utils.py
python_libpcap.egg-info/PKG-INFO
python_libpcap.egg-info/SOURCES.txt
python_libpcap.egg-info/dependency_links.txt
python_libpcap.egg-info/entry_points.txt
python_libpcap.egg-info/not-zip-safe
python_libpcap.egg-info/requires.txt
python_libpcap.egg-info/top_level.txt
requirements/base.txt
requirements/dev.txt
requirements/publish.txt
requirements/test.txt