Metadata-Version: 2.1
Name: python-libpcap
Version: 0.4.2
Summary: Cython libpcap
Home-page: https://github.com/caizhengxin/python-libpcap
Author: JanKinCai
Author-email: jankincai12@gmail.com
Maintainer: JanKinCai
Maintainer-email: jankincai12@gmail.com
License: BSD
Download-URL: https://github.com/caizhengxin/python-libpcap.git
Project-URL: Documentation, https://python-libpcap.readthedocs.io
Project-URL: Source Code, https://github.com/caizhengxin/python-libpcap
Keywords: python-libpcap,pylibpcap,libpcap,pcap,pcapngpython,libpcap-python,python-pcapng
Platform: Linux
Classifier: Development Status :: 4 - Beta
Classifier: Operating System :: OS Independent
Classifier: Intended Audience :: Developers
Classifier: License :: OSI Approved :: BSD License
Classifier: Programming Language :: Python
Classifier: Programming Language :: Python :: Implementation
Classifier: Programming Language :: Python :: 3
Classifier: Programming Language :: Python :: 3.6
Classifier: Programming Language :: Python :: 3.7
Classifier: Topic :: Software Development :: Libraries
License-File: LICENSE
